{
  "year_month": "2025-11",
  "guild": "beQuiet",
  "kills": {
    "GeorgeDroid": 187849,
    "marryme": 210661,
    "FarmerJoe": 158581,
    "Albert": 145548,
    "Beef": 46118,
    "Kosabi": 47057,
    "Schwanger": 30981,
    "Manamy": 23130,
    "Duweiss": 10153,
    "Soup": 20628,
    "Sunraku": 6194,
    "Grindr": 14805,
    "Beater": 13959,
    "Tempest": 2171,
    "Diaz": 2736,
    "Auralion": 13431,
    "Nalah": 4802,
    "AntsInThePants": 4816,
    "Stride": 1206,
    "HookahHunter": 2276,
    "Undine": 14385,
    "Litus": 32285,
    "Endorphin": 2472,
    "T1tan": 12647,
    "Hauge": 5911,
    "Tamr": 1597,
    "Xless": 3418,
    "Boniface": 5167,
    "Rassyx": 62,
    "Joko": 1281,
    "Davies": 1012
  }
}