{
  "date": "2025-11-25",
  "kills": {
    "Hauge": 2741,
    "Kosabi": 2620,
    "Adrenalized": 2360,
    "Gudde": 1486,
    "MarryJay": 1426,
    "SoloDingens": 907,
    "Phelenxs": 804,
    "GetOnTheGroundMrPr": 697,
    "Elena": 538,
    "Kobold": 522,
    "Nymphetamine": 319,
    "Yuiy": 239,
    "Cattingsku": 226,
    "T1tan": 171,
    "Schwanger": 153,
    "Sunraku": 68,
    "Frosch": 66,
    "Algiz": 58,
    "Glinda": 45,
    "Urmack": 39,
    "Mmmmm": 34,
    "Hafren": 33,
    "Aurora": 15,
    "Catting": 4,
    "Mirina": 3,
    "AntsInThePants": 2
  }
}